circleguard/__init__.py
circleguard/circleguard.py
circleguard/frametime_graph.py
circleguard/game_version.py
circleguard/hitobjects.py
circleguard/investigations.py
circleguard/judgment.py
circleguard/loadables.py
circleguard/loader.py
circleguard/map_info.py
circleguard/mod.py
circleguard/postgres.py
circleguard/span.py
circleguard/utils.py
circleguard/version.py
tests/__init__.py
tests/benchmark_hits.py
tests/benchmarks.py
tests/pool.py
tests/test_investigations.py
tests/test_keyless_circleguard.py
tests/test_loadables.py
tests/test_loader.py
tests/test_mod.py
tests/test_properties.py
tests/utils.py
circleguard-5.4.3.dist-info/LICENSE
circleguard-5.4.3.dist-info/METADATA
circleguard-5.4.3.dist-info/WHEEL
circleguard-5.4.3.dist-info/top_level.txt
circleguard-5.4.3.dist-info/RECORD
