Metadata-Version: 2.1
Name: circleguard
Version: 5.4.3
Summary: A utilities library for osu!. Provides support for parsing replays from a file or from the api, as well as support for unstable rate, hits, similarity, and frametime calculations.
Home-page: https://github.com/circleguard/circlecore
Download-URL: https://github.com/circleguard/circlecore/tarball/v5.4.3
Author: Liam DeVoe
Author-email: orionldevoe@gmail.com
Keywords: osu!, python, cheat-detection, replay-stealing, remodding
Classifier: Programming Language :: Python :: 3
Classifier: Intended Audience :: Developers
Classifier: License :: OSI Approved :: GNU General Public License v3 (GPLv3)
Classifier: Operating System :: OS Independent
License-File: LICENSE
Requires-Dist: osrparse ~=6.0
Requires-Dist: ossapi <5.0.0,>=3.0.0
Requires-Dist: wtc ==1.2.1
Requires-Dist: numpy
Requires-Dist: requests
Requires-Dist: slider >=0.5.1
Requires-Dist: scipy
Provides-Extra: graphing
Requires-Dist: matplotlib ; extra == 'graphing'
